selsunpool/__init__.py
selsunpool/config.py
selsunpool/executor.py
tests/__init__.py
tests/context.py
tests/testbasic.py
selsunpool-0.0.1.dist-info/LICENSE
selsunpool-0.0.1.dist-info/METADATA
selsunpool-0.0.1.dist-info/WHEEL
selsunpool-0.0.1.dist-info/top_level.txt
selsunpool-0.0.1.dist-info/RECORD
